intervalues_pyrust.cpython-311-x86_64-linux-gnu.so
intervalues/combine_intervals.py
intervalues/interval_pdf.py
intervalues/interval_set.py
intervalues/abstract_interval.py
intervalues/base_interval_discrete.py
intervalues/__version__.py
intervalues/base_interval.py
intervalues/__init__.py
intervalues/interval_list.py
intervalues/interval_meter.py
intervalues-0.3.0.dist-info/LICENSE
intervalues-0.3.0.dist-info/RECORD
intervalues-0.3.0.dist-info/top_level.txt
intervalues-0.3.0.dist-info/METADATA
intervalues-0.3.0.dist-info/WHEEL
