Metadata-Version: 2.1
Name: intervalues
Version: 0.3.0
Summary: Efficient combining of intervals of numbers.
Home-page: https://gitlab.com/bert.debruijn/intervalues
Author: Bert de Bruijn
Author-email: Bert de Bruijn <lpdebruijn@gmail.com>
Project-URL: Homepage, https://gitlab.com/bert.debruijn/intervalues
Project-URL: Issues, https://gitlab.com/bert.debruijn/intervalues/-/issues
Classifier: Programming Language :: Python :: 3
Classifier: License :: OSI Approved :: MIT License
Classifier: Operating System :: OS Independent
Requires-Python: ~=3.10
License-File: LICENSE
